CHANGES.rst
MANIFEST.in
README.md
setup.py
collective/__init__.py
collective.passwordwall.egg-info/PKG-INFO
collective.passwordwall.egg-info/SOURCES.txt
collective.passwordwall.egg-info/dependency_links.txt
collective.passwordwall.egg-info/entry_points.txt
collective.passwordwall.egg-info/namespace_packages.txt
collective.passwordwall.egg-info/not-zip-safe
collective.passwordwall.egg-info/requires.txt
collective.passwordwall.egg-info/top_level.txt
collective/passwordwall/__init__.py
collective/passwordwall/configure.zcml
collective/passwordwall/handlers.py
collective/passwordwall/interfaces.py
collective/passwordwall/passwordwall_form.pt
collective/passwordwall/plonecontrolpanel.py
collective/passwordwall/settings.py
collective/passwordwall/utils.py
collective/passwordwall/views.py