Metadata-Version: 1.1
Name: collective.passwordwall
Version: 0.1a1
Summary: Passwordwall plugin
Home-page: https://github.com/fourdigits/collective.passwordwall/
Author: Kees Hink
Author-email: kees@fourdigits.nl
License: GPLv3
Platform: UNKNOWN
Classifier: Framework :: Plone
Classifier: Framework :: Plone :: 4.3
Classifier: Programming Language :: Python
Classifier: Programming Language :: Python :: 2
Classifier: Programming Language :: Python :: 2.7
